my_lib_gens/__init__.py
my_lib_gens/_add.py
my_lib_gens/_divide.py
my_lib_gens/_modulo.py
my_lib_gens/_multiply.py
my_lib_gens/_sub.py
my_lib_gens-0.0.6.dist-info/METADATA
my_lib_gens-0.0.6.dist-info/WHEEL
my_lib_gens-0.0.6.dist-info/licenses/LICENSE
my_lib_gens-0.0.6.dist-info/RECORD
